mtmflow/__init__.py
mtmflow/__main__.py
mtmflow/api/__init__.py
mtmflow/api/hello.py
mtmflow/api/main.py
mtmflow/cli/__init__.py
mtmflow/cli/install.py
mtmflow/cli/serve.py
mtmflow/core/__init__.py
mtmflow/core/__version__.py
mtmflow/core/config.py
mtmflow-0.0.392.dist-info/METADATA
mtmflow-0.0.392.dist-info/WHEEL
mtmflow-0.0.392.dist-info/entry_points.txt
mtmflow-0.0.392.dist-info/RECORD
