Metadata-Version: 2.1
Name: mtmflow
Version: 0.0.392
Summary: 
License: MIT
Author: John Smith
Author-email: john@example.com
Requires-Python: >=3.10,<3.13
Classifier: License :: OSI Approved :: MIT License
Classifier: Programming Language :: Python :: 3
Classifier: Programming Language :: Python :: 3.10
Classifier: Programming Language :: Python :: 3.11
Classifier: Programming Language :: Python :: 3.12
Requires-Dist: fastapi (>=0.104.1)
Requires-Dist: langflow (>=1.0.17,<2.0.0)
